topsis/__init__.py
topsis/topsis.py
topsis_102103596-0.2.dist-info/LICENSE
topsis_102103596-0.2.dist-info/METADATA
topsis_102103596-0.2.dist-info/WHEEL
topsis_102103596-0.2.dist-info/top_level.txt
topsis_102103596-0.2.dist-info/RECORD
